<?xml version="1.0" encoding="utf-8" ?>
<dwsync>
<file name="upset.php" server="D:/WWW/ExamOnline/" local="130312500737871693" remote="130312500730000000" Dst="0" />
<file name="student.php" server="D:/WWW/ExamOnline/" local="130313145975329850" remote="130313145970000000" Dst="0" />
<file name="upsetpwd.php" server="D:/WWW/ExamOnline/" local="130312502205905660" remote="130312502200000000" Dst="0" />
<file name="修改密码界面.html" server="D:/WWW/ExamOnline/" local="130312504852377030" remote="130312504850000000" Dst="0" />
<file name="补考查询界面.html" server="D:/WWW/ExamOnline/" local="130312504854437148" remote="130312504850000000" Dst="0" />
<file name="examscore.php" server="D:/WWW/ExamOnline/" local="130313145740686429" remote="130313145740000000" Dst="0" />
<file name="examscore.php" server="D:/WWW/" local="130334086133405500" remote="130334086130000000" Dst="0" />
<file name="upsetpwd.php" server="D:/WWW/" local="130331258655171973" remote="130331258650000000" Dst="0" />
<file name="修改密码界面.html" server="D:/WWW/" local="130334086132565452" remote="130334086130000000" Dst="0" />
<file name="upset.php" server="D:/WWW/" local="130332243952414973" remote="130332243950000000" Dst="0" />
<file name="student.php" server="D:/WWW/" local="130334086133775521" remote="130334086130000000" Dst="0" />
<file name="time.php" server="D:/WWW/" local="130331225724974540" remote="130331225720000000" Dst="0" />
<file name="leftframe.php" server="D:/WWW/" local="130331234938133186" remote="130331234930000000" Dst="0" />
<file name="oclock.php" server="D:/WWW/" local="130331223775267406" remote="130331223770000000" Dst="0" />
<file name="top.php" server="D:/WWW/" local="130331256701960255" remote="130331256700000000" Dst="0" />
<file name="补考查询界面.html" server="D:/WWW/" local="130334086132205431" remote="130334086130000000" Dst="0" />
<file name="index.html" server="D:/WWW/" local="130334099926044394" remote="130334099920000000" Dst="0" />
<file name="rightframe.php" server="D:/WWW/" local="130334090824053790" remote="130334090820000000" Dst="0" />
<file name="rightframesave.php" server="D:/WWW/" local="130334113443507549" remote="130334113440000000" Dst="0" />
</dwsync>